{
  "$schema": "https://raw.githubusercontent.com/grafana/grafana/master/docs/sources/developers/plugins/plugin.schema.json",
  "dependencies": {
    "grafanaDependency": ">=8.5.0",
    "plugins": []
  },
  "id": "volkovlabs-supervisor-datasource",
  "info": {
    "author": {
      "name": "Volkov Labs",
      "url": "https://volkovlabs.io"
    },
    "description": "Balena Supervisor API",
    "keywords": ["balena"],
    "links": [
      {
        "name": "Website",
        "url": "https://volkovlabs.io"
      }
    ],
    "logos": {
      "large": "img/logo.svg",
      "small": "img/logo.svg"
    },
    "screenshots": [],
    "updated": "%TODAY%",
    "version": "%VERSION%"
  },
  "logs": true,
  "metrics": true,
  "name": "Balena Supervisor",
  "routes": [
    {
      "method": "GET",
      "path": "ping",
      "reqRole": "Viewer",
      "url": "{{ .JsonData.url }}/ping"
    },
    {
      "method": "*",
      "path": "v1",
      "reqRole": "Viewer",
      "url": "{{ .JsonData.url }}/v1",
      "urlParams": [
        {
          "content": "{{ .SecureJsonData.apiKey }}",
          "name": "apikey"
        }
      ]
    },
    {
      "method": "*",
      "path": "v2",
      "reqRole": "Viewer",
      "url": "{{ .JsonData.url }}/v2",
      "urlParams": [
        {
          "content": "{{ .SecureJsonData.apiKey }}",
          "name": "apikey"
        }
      ]
    }
  ],
  "type": "datasource"
}
